mopidy_soundcloud/__init__.py
mopidy_soundcloud/actor.py
mopidy_soundcloud/ext.conf
mopidy_soundcloud/library.py
mopidy_soundcloud/soundcloud.py
Mopidy_SoundCloud-3.0.2.dist-info/LICENSE
Mopidy_SoundCloud-3.0.2.dist-info/METADATA
Mopidy_SoundCloud-3.0.2.dist-info/WHEEL
Mopidy_SoundCloud-3.0.2.dist-info/entry_points.txt
Mopidy_SoundCloud-3.0.2.dist-info/top_level.txt
Mopidy_SoundCloud-3.0.2.dist-info/RECORD
